orn/__main__.py
orn/cli/__init__.py
orn/cli/commands/__init__.py
orn/cli/commands/about.py
orn/cli/commands/add.py
orn/cli/commands/build.py
orn/cli/commands/create.py
orn/cli/commands/init.py
orn/cli/commands/lock.py
orn/cli/commands/test.py
orn/py.typed
orn-0.1.0.dist-info/LICENSE
orn-0.1.0.dist-info/METADATA
orn-0.1.0.dist-info/WHEEL
orn-0.1.0.dist-info/entry_points.txt
orn-0.1.0.dist-info/RECORD
